prompt_ast/__init__.py
prompt_ast/ast.py
prompt_ast/cli.py
prompt_ast/errors.py
prompt_ast/formats.py
prompt_ast/llm/__init__.py
prompt_ast/llm/base.py
prompt_ast/llm/openai_compat.py
prompt_ast/parse/__init__.py
prompt_ast/parse/heuristic.py
prompt_ast/parse/heuristic.py.backup
prompt_ast/parse/hybrid.py
prompt_ast/parse/llm.py
prompt_ast-0.2.4.dist-info/METADATA
prompt_ast-0.2.4.dist-info/WHEEL
prompt_ast-0.2.4.dist-info/entry_points.txt
prompt_ast-0.2.4.dist-info/licenses/LICENSE
prompt_ast-0.2.4.dist-info/RECORD
