Metadata-Version: 2.4
Name: prompt-ast
Version: 0.2.4
Summary: Parse free-form human prompts into a canonical Prompt AST (structured JSON/YAML).
License: MIT
License-File: LICENSE
Author: Chvrr
Requires-Python: >=3.11
Classifier: License :: OSI Approved :: MIT License
Classifier: Programming Language :: Python :: 3
Classifier: Programming Language :: Python :: 3.11
Classifier: Programming Language :: Python :: 3.12
Classifier: Programming Language :: Python :: 3.13
Classifier: Programming Language :: Python :: 3.14
Provides-Extra: all
Provides-Extra: openai
Provides-Extra: yaml
Requires-Dist: httpx (>=0.27,<1.0) ; extra == "all"
Requires-Dist: httpx (>=0.27,<1.0) ; extra == "openai"
Requires-Dist: httpx (>=0.28.1,<0.29.0)
Requires-Dist: pydantic (>=2.7,<3.0)
Requires-Dist: pyyaml (>=6.0.1,<7.0) ; extra == "all"
Requires-Dist: pyyaml (>=6.0.1,<7.0) ; extra == "yaml"
Requires-Dist: pyyaml (>=6.0.3,<7.0.0)
Requires-Dist: rich (>=13.7,<15.0)
Requires-Dist: typer (>=0.12,<1.0)
Project-URL: Documentation, https://github.com/chvr4ai-hub/prompt-ast/tree/main/docs/index.md
Project-URL: Homepage, https://github.com/chvr4ai-hub/prompt-ast
Project-URL: Issues, https://github.com/chvr4ai-hub/prompt-ast/issues
Project-URL: Repository, https://github.com/chvr4ai-hub/prompt-ast
